valthos_sdk/__init__.py
valthos_sdk/sdk/__init__.py
valthos_sdk/sdk/auth.py
valthos_sdk/sdk/client.py
valthos_sdk/sdk/exceptions.py
valthos_sdk/sdk/models.py
valthos_sdk/sdk/session.py
valthos_sdk/sdk/workspace.py
valthos_sdk/tools/__init__.py
valthos_sdk/tools/base.py
valthos_sdk/tools/genome_profiling.py
valthos_sdk/tools/protein_profiling.py
valthos_sdk/tools/sequence_search.py
valthos_sdk-0.1.1.dist-info/licenses/LICENSE
valthos_sdk-0.1.1.dist-info/METADATA
valthos_sdk-0.1.1.dist-info/WHEEL
valthos_sdk-0.1.1.dist-info/top_level.txt
valthos_sdk-0.1.1.dist-info/RECORD
