Metadata-Version: 2.4
Name: valthos-sdk
Version: 0.1.1
Summary: Python SDK for Valthos API
Author-email: Valthos <support@valthos.com>
License-Expression: MIT
Project-URL: Homepage, https://valthos.com
Project-URL: Documentation, https://docs.valthos.com
Project-URL: Repository, https://github.com/valthos/valthos-sdk
Classifier: Development Status :: 3 - Alpha
Classifier: Intended Audience :: Developers
Classifier: Programming Language :: Python :: 3
Classifier: Programming Language :: Python :: 3.8
Classifier: Programming Language :: Python :: 3.9
Classifier: Programming Language :: Python :: 3.10
Classifier: Programming Language :: Python :: 3.11
Classifier: Programming Language :: Python :: 3.12
Requires-Python: >=3.8
License-File: LICENSE
Requires-Dist: requests>=2.25.0
Requires-Dist: pydantic>=1.8.0
Dynamic: license-file
